removestar/__init__.py
removestar/__main__.py
removestar/_version.py
removestar/helper.py
removestar/output.py
removestar/removestar.py
removestar/version.pyi
removestar-1.4.dist-info/METADATA
removestar-1.4.dist-info/WHEEL
removestar-1.4.dist-info/entry_points.txt
removestar-1.4.dist-info/licenses/LICENSE
removestar-1.4.dist-info/RECORD
