Metadata-Version: 2.1
Name: removestar
Version: 1.4
Summary: A tool to automatically replace 'import *' imports with explicit imports in files
Project-URL: Bug Tracker, https://github.com/asmeurer/removestar/issues
Project-URL: Homepage, https://www.asmeurer.com/removestar/
Project-URL: Source Code, https://github.com/asmeurer/removestar
Author-email: Aaron Meurer <asmeurer@gmail.com>
Maintainer-email: Aaron Meurer <asmeurer@gmail.com>, Saransh Chopra <saransh0701@gmail.com>
License-Expression: MIT
License-File: LICENSE
Classifier: Development Status :: 5 - Production/Stable
Classifier: License :: OSI Approved :: MIT License
Classifier: Operating System :: OS Independent
Classifier: Programming Language :: Python
Classifier: Programming Language :: Python :: 3 :: Only
Classifier: Programming Language :: Python :: 3.8
Classifier: Programming Language :: Python :: 3.9
Classifier: Programming Language :: Python :: 3.10
Classifier: Programming Language :: Python :: 3.11
Requires-Python: >=3.7
Requires-Dist: pyflakes
Provides-Extra: dev
Requires-Dist: pytest-cov>=3; extra == 'dev'
Requires-Dist: pytest-doctestplus; extra == 'dev'
Requires-Dist: pytest>=6; extra == 'dev'
